bonobo_sqlalchemy/__init__.py
bonobo_sqlalchemy/_api.py
bonobo_sqlalchemy/_version.py
bonobo_sqlalchemy/constants.py
bonobo_sqlalchemy/errors.py
bonobo_sqlalchemy/logging.py
bonobo_sqlalchemy/readers.py
bonobo_sqlalchemy/util.py
bonobo_sqlalchemy/writers.py
bonobo_sqlalchemy-0.6.1.dist-info/METADATA
bonobo_sqlalchemy-0.6.1.dist-info/RECORD
bonobo_sqlalchemy-0.6.1.dist-info/WHEEL
bonobo_sqlalchemy-0.6.1.dist-info/top_level.txt
