Metadata-Version: 2.1
Name: bonobo-sqlalchemy
Version: 0.6.1
Summary: Bonobo SQLAlchemy Extension
Home-page: https://www.bonobo-project.org/with/sqlalchemy
Author: Romain Dorgueil
Author-email: romain@dorgueil.net
License: Apache License, Version 2.0
Download-URL: https://github.com/python-bonobo/bonobo-sqlalchemy/tarball/0.6.1
Platform: UNKNOWN
Requires-Python: >=3.5
Provides-Extra: dev
Requires-Dist: SQLAlchemy (~=1.2)
Requires-Dist: bonobo (~=0.6.0)
Provides-Extra: dev
Requires-Dist: bonobo[dev] (~=0.6.0); extra == 'dev'
Requires-Dist: coverage (~=4.4); extra == 'dev'
Requires-Dist: pytest (~=3.4); extra == 'dev'
Requires-Dist: pytest-cov (~=2.5); extra == 'dev'
Requires-Dist: yapf; extra == 'dev'
